jinjazzle/__init__.py
jinjazzle/ext/__init__.py
jinjazzle/ext/python.py
jinjazzle/ext/string.py
jinjazzle/ext/uuid.py
jinjazzle/ext/version.py
jinjazzle-1.2.4.dist-info/licenses/LICENSE
jinjazzle-1.2.4.dist-info/METADATA
jinjazzle-1.2.4.dist-info/WHEEL
jinjazzle-1.2.4.dist-info/entry_points.txt
jinjazzle-1.2.4.dist-info/top_level.txt
jinjazzle-1.2.4.dist-info/zip-safe
jinjazzle-1.2.4.dist-info/RECORD
