Metadata-Version: 2.4
Name: jinjazzle
Version: 1.2.4
Summary: Jinja2 extensions
Author-email: Julien Lecomte <julien@lecomte.at>
License: MIT
Project-URL: Homepage, https://gitlab.com/cappysan/jinjazzle
Project-URL: Documentation, https://jinjazzle.docs.cappysan.dev
Project-URL: Source code, https://gitlab.com/cappysan/jinjazzle
Project-URL: Bug tracker, https://gitlab.com/cappysan/jinjazzle/-/issues
Project-URL: Changelog, https://gitlab.com/cappysan/jinjazzle/-/raw/main/CHANGELOG.md
Classifier: License :: OSI Approved :: MIT License
Classifier: Development Status :: 5 - Production/Stable
Classifier: Programming Language :: Python :: 3 :: Only
Classifier: Programming Language :: Python :: 3.9
Classifier: Programming Language :: Python :: 3.10
Classifier: Programming Language :: Python :: 3.11
Classifier: Programming Language :: Python :: 3.12
Classifier: Programming Language :: Python :: 3.13
Requires-Python: >=3.9
License-File: LICENSE
Requires-Dist: jinja2>=3.0.0
Requires-Dist: python-slugify>=7.0.0
Dynamic: license-file
